website2md/__init__.py
website2md/__main__.py
website2md/cli.py
website2md/config.py
website2md/crawler.py
website2md/doc_crawler.py
website2md/url_file_crawler.py
website2md/url_list_crawler.py
website2md/utils.py
website2md-0.1.8.dist-info/licenses/LICENSE
website2md-0.1.8.dist-info/METADATA
website2md-0.1.8.dist-info/WHEEL
website2md-0.1.8.dist-info/entry_points.txt
website2md-0.1.8.dist-info/top_level.txt
website2md-0.1.8.dist-info/RECORD
