Metadata-Version: 2.4
Name: website2md
Version: 0.1.8
Summary: Convert websites to markdown format using crawl4ai framework
Author-email: fxy <fxy@example.com>
License-Expression: MIT
Project-URL: Homepage, https://github.com/fengyunzaidushi/website2md
Project-URL: Repository, https://github.com/fengyunzaidushi/website2md
Project-URL: Issues, https://github.com/fengyunzaidushi/website2md/issues
Classifier: Development Status :: 3 - Alpha
Classifier: Intended Audience :: Developers
Classifier: Programming Language :: Python :: 3
Classifier: Programming Language :: Python :: 3.10
Classifier: Programming Language :: Python :: 3.11
Classifier: Programming Language :: Python :: 3.12
Requires-Python: >=3.10
License-File: LICENSE
Requires-Dist: crawl4ai>=0.6.0
Requires-Dist: requests>=2.31.0
Requires-Dist: beautifulsoup4>=4.12.0
Requires-Dist: lxml>=4.9.0
Requires-Dist: aiohttp>=3.8.0
Requires-Dist: python-dotenv>=1.0.0
Requires-Dist: click>=8.1.0
Requires-Dist: twine>=6.1.0
Requires-Dist: build>=1.2.2.post1
Provides-Extra: dev
Requires-Dist: pytest>=7.0.0; extra == "dev"
Requires-Dist: pytest-asyncio>=0.21.0; extra == "dev"
Requires-Dist: black>=23.0.0; extra == "dev"
Requires-Dist: flake8>=6.0.0; extra == "dev"
Requires-Dist: mypy>=1.0.0; extra == "dev"
Dynamic: license-file
